llamatune/__init__.py
llamatune/train.py
llamatune/trainer.py
llamatune/utils.py
llamatune/data/__init__.py
llamatune/data/chat_data_module.py
llamatune/data/data_module.py
llamatune/model_engines/__init__.py
llamatune/model_engines/llama_model_engine.py
llamatune/telemetry/__init__.py
llamatune/telemetry/send_event.py
llamatune-0.4.0.dist-info/METADATA
llamatune-0.4.0.dist-info/WHEEL
llamatune-0.4.0.dist-info/top_level.txt
llamatune-0.4.0.dist-info/RECORD
